[
  {
    "title": "task 4",
    "description": "task 4 desc",
    "status": "TO_DO",
    "username": "",
    "createdAt": "",
    "updatedAt": ""
  },
  {
    "title": "task 5",
    "description": "task 5 desc",
    "status": "DONE",
    "username": "ysp",
    "createdAt": "2025-10-22T17:22:46.249Z",
    "updatedAt": "2025-10-22T17:22:46.249Z"
  },
  {
    "title": "task 6",
    "description": "task 6 desc",
    "status": "TO_DO",
    "username": "ysp",
    "createdAt": "2025-10-22T17:27:41.076Z",
    "updatedAt": "2025-10-22T17:27:41.076Z"
  }
]